{"LevelsProgress":[{"world":1,"level":1,"starsEarned":0,"highscore":0},{"world":1,"level":2,"starsEarned":0,"highscore":0},{"world":1,"level":3,"starsEarned":0,"highscore":0},{"world":2,"level":1,"starsEarned":0,"highscore":0},{"world":2,"level":2,"starsEarned":0,"highscore":0},{"world":2,"level":3,"starsEarned":0,"highscore":0},{"world":3,"level":1,"starsEarned":0,"highscore":0},{"world":3,"level":2,"starsEarned":0,"highscore":0},{"world":3,"level":3,"starsEarned":0,"highscore":0},{"world":4,"level":1,"starsEarned":0,"highscore":0},{"world":4,"level":2,"starsEarned":0,"highscore":0},{"world":4,"level":3,"starsEarned":0,"highscore":0},{"world":5,"level":1,"starsEarned":0,"highscore":0},{"world":5,"level":2,"starsEarned":0,"highscore":0},{"world":5,"level":3,"starsEarned":0,"highscore":0},{"world":6,"level":1,"starsEarned":0,"highscore":0},{"world":6,"level":2,"starsEarned":0,"highscore":0},{"world":6,"level":3,"starsEarned":0,"highscore":0},{"world":7,"level":1,"starsEarned":0,"highscore":0},{"world":7,"level":2,"starsEarned":0,"highscore":0},{"world":7,"level":3,"starsEarned":0,"highscore":0},{"world":8,"level":1,"starsEarned":0,"highscore":0},{"world":8,"level":2,"starsEarned":0,"highscore":0},{"world":8,"level":3,"starsEarned":0,"highscore":0},{"world":9,"level":1,"starsEarned":0,"highscore":0},{"world":9,"level":2,"starsEarned":0,"highscore":0},{"world":9,"level":3,"starsEarned":0,"highscore":0},{"world":10,"level":1,"starsEarned":0,"highscore":0},{"world":10,"level":2,"starsEarned":0,"highscore":0},{"world":10,"level":3,"starsEarned":0,"highscore":0},{"world":11,"level":1,"starsEarned":0,"highscore":0},{"world":11,"level":2,"starsEarned":0,"highscore":0},{"world":11,"level":3,"starsEarned":0,"highscore":0},{"world":12,"level":1,"starsEarned":0,"highscore":0},{"world":12,"level":2,"starsEarned":0,"highscore":0},{"world":12,"level":3,"starsEarned":0,"highscore":0},{"world":13,"level":1,"starsEarned":0,"highscore":0},{"world":13,"level":2,"starsEarned":0,"highscore":0},{"world":13,"level":3,"starsEarned":0,"highscore":0},{"world":14,"level":1,"starsEarned":0,"highscore":0},{"world":14,"level":2,"starsEarned":0,"highscore":0},{"world":14,"level":3,"starsEarned":0,"highscore":0}]}